README.rst
blobs.cfg
bootstrap.py
buildout.cfg
plone-4.cfg
setup.py
Products/__init__.py
Products.ImageEditor.egg-info/PKG-INFO
Products.ImageEditor.egg-info/SOURCES.txt
Products.ImageEditor.egg-info/dependency_links.txt
Products.ImageEditor.egg-info/entry_points.txt
Products.ImageEditor.egg-info/namespace_packages.txt
Products.ImageEditor.egg-info/not-zip-safe
Products.ImageEditor.egg-info/requires.txt
Products.ImageEditor.egg-info/top_level.txt
Products/ImageEditor/__init__.py
Products/ImageEditor/configure.zcml
Products/ImageEditor/importexport.py
Products/ImageEditor/profiles.zcml
Products/ImageEditor/subscribers.py
Products/ImageEditor/testing.py
Products/ImageEditor/testing.zcml
Products/ImageEditor/translationstrings.py
Products/ImageEditor/upgrades.py
Products/ImageEditor/upgrades.zcml
Products/ImageEditor/utils.py
Products/ImageEditor/version.txt
Products/ImageEditor/vocabularies.py
Products/ImageEditor/actions/__init__.py
Products/ImageEditor/actions/actions.py
Products/ImageEditor/actions/base.py
Products/ImageEditor/actions/configure.zcml
Products/ImageEditor/actions/options.py
Products/ImageEditor/actions/sliderwidget.pt
Products/ImageEditor/actions/widgets.py
Products/ImageEditor/adapters/__init__.py
Products/ImageEditor/adapters/configure.zcml
Products/ImageEditor/adapters/imageeditor.py
Products/ImageEditor/browser/__init__.py
Products/ImageEditor/browser/alagimp.pt
Products/ImageEditor/browser/alagimp.py
Products/ImageEditor/browser/base.py
Products/ImageEditor/browser/configure.zcml
Products/ImageEditor/browser/css.zcml
Products/ImageEditor/browser/imageeditor.py
Products/ImageEditor/browser/inline.pt
Products/ImageEditor/browser/resources/alagimp.css
Products/ImageEditor/browser/resources/alagimp.js
Products/ImageEditor/browser/resources/editlink.js
Products/ImageEditor/browser/resources/inline.css
Products/ImageEditor/browser/resources/icons/actions_background.jpg
Products/ImageEditor/browser/resources/icons/apply.png
Products/ImageEditor/browser/resources/icons/edit-redo.png
Products/ImageEditor/browser/resources/icons/edit-undo.png
Products/ImageEditor/browser/resources/icons/process-stop.png
Products/ImageEditor/browser/resources/icons/stock-resize-16.png
Products/ImageEditor/browser/resources/icons/stock-rotate-270-16.png
Products/ImageEditor/browser/resources/icons/stock-rotate-90-16.png
