Metadata-Version: 1.0
Name: Products.ImageEditor
Version: 3.0.0
Summary: adds a "Image Editor" link near the image widget  allowing the user to rotate, flip, blur, compress, change contrast & brightness, sharpen, add drop shadows, crop, resize an image, save as, and apply sepia.
Home-page: http://www.plone.org/products/products-imageeditor
Author: Nathan Van Gheem
Author-email: vangheem@gmail.com
License: GPL
Keywords: plone image editor rotate flip blur compress contrast brightness sharpen drop shadows crop resize save as sepia
Platform: UNKNOWN
Classifier: Development Status :: 4 - Beta
Classifier: Framework :: Plone :: 4.0
Classifier: Framework :: Plone :: 4.1
Classifier: Framework :: Plone :: 4.2
Classifier: Framework :: Plone :: 4.3
Classifier: License :: OSI Approved :: GNU General Public License (GPL)
Classifier: Operating System :: OS Independent
Classifier: Programming Language :: JavaScript
Classifier: Programming Language :: Python
Classifier: Topic :: Software Development :: Libraries :: Python Modules
